altitude_analisis/__init__.py
altitude_analisis/altitude_a.cp312-win_amd64.pyd
altitude_analisis-6.6.6.dist-info/licenses/LICENSE
altitude_analisis-6.6.6.dist-info/METADATA
altitude_analisis-6.6.6.dist-info/WHEEL
altitude_analisis-6.6.6.dist-info/entry_points.txt
altitude_analisis-6.6.6.dist-info/top_level.txt
altitude_analisis-6.6.6.dist-info/RECORD
